reflex_mouse_track/__init__.py
reflex_mouse_track/mouse_track.py
reflex_mouse_track-0.0.1.dist-info/METADATA
reflex_mouse_track-0.0.1.dist-info/WHEEL
reflex_mouse_track-0.0.1.dist-info/top_level.txt
reflex_mouse_track-0.0.1.dist-info/RECORD
