Metadata-Version: 2.1
Name: reflex-mouse-track
Version: 0.0.1
Summary: Reflex custom component mouse-track
Author-email: Your Name <thomas.brandeho@gmail.com>
License: Apache-2.0
Project-URL: Homepage, https://github.com/Lendemor/reflex-mouse-track/
Keywords: reflex,reflex-custom-components
Classifier: Development Status :: 4 - Beta
Requires-Python: >=3.9
Requires-Dist: reflex>=0.6.7
Provides-Extra: dev
Requires-Dist: build; extra == "dev"
Requires-Dist: twine; extra == "dev"
